{
  "project_info": {
    "project_number": "710486882151",
    "project_id": "sfltimer",
    "storage_bucket": "sfltimer.appspot.com"
  },
  "client": [
    {
      "client_info": {
        "mobilesdk_app_id": "1:710486882151:android:261aecbc443ffe112321c2",
        "android_client_info": {
          "package_name": "com.john4e656f.sunflowerlandtimerapp"
        }
      },
      "oauth_client": [
        {
          "client_id": "710486882151-d68hmuf03b2m158firvi3jrfps301n16.apps.googleusercontent.com",
          "client_type": 3
        }
      ],
      "api_key": [
        {
          "current_key": "AIzaSyA7hcucqjgB4icdOCYIxLDQqAaaI3KorAk"
        }
      ],
      "services": {
        "appinvite_service": {
          "other_platform_oauth_client": [
            {
              "client_id": "710486882151-d68hmuf03b2m158firvi3jrfps301n16.apps.googleusercontent.com",
              "client_type": 3
            }
          ]
        }
      }
    }
  ],
  "configuration_version": "1"
}
